README.txt
setup.cfg
setup.py
docs/HISTORY.txt
docs/INSTALL.txt
docs/LICENSE.GPL
docs/LICENSE.txt
my315ok/__init__.py
my315ok.portlet.bookmark.egg-info/PKG-INFO
my315ok.portlet.bookmark.egg-info/SOURCES.txt
my315ok.portlet.bookmark.egg-info/dependency_links.txt
my315ok.portlet.bookmark.egg-info/entry_points.txt
my315ok.portlet.bookmark.egg-info/namespace_packages.txt
my315ok.portlet.bookmark.egg-info/not-zip-safe
my315ok.portlet.bookmark.egg-info/requires.txt
my315ok.portlet.bookmark.egg-info/top_level.txt
my315ok/portlet/__init__.py
my315ok/portlet/bookmark/__init__.py
my315ok/portlet/bookmark/bookmarkportlet.pt
my315ok/portlet/bookmark/bookmarkportlet.py
my315ok/portlet/bookmark/configure.zcml
my315ok/portlet/bookmark/version.txt
my315ok/portlet/bookmark/i18n/plone-zh.po
my315ok/portlet/bookmark/i18n/plone.pot
my315ok/portlet/bookmark/locales/bookmark.pot
my315ok/portlet/bookmark/locales/zh/LC_MESSAGES/my315ok.portlet.bookmark.mo
my315ok/portlet/bookmark/locales/zh/LC_MESSAGES/my315ok.portlet.bookmark.po
my315ok/portlet/bookmark/profiles/default/metadata.xml
my315ok/portlet/bookmark/profiles/default/portlets.xml
my315ok/portlet/bookmark/tests/__init__.py
my315ok/portlet/bookmark/tests/base.py
my315ok/portlet/bookmark/tests/test_portlet.py
