Metadata-Version: 1.0
Name: my315ok.portlet.bookmark
Version: 1.0dev-r136
Summary: A bookmark portlet
Home-page: http://oa.315ok.org/
Author: adam tang
Author-email: yuejun.tang@gmail.com
License: GPL
Keywords: portlet bookmark tag
Platform: UNKNOWN
Classifier: Framework :: Plone
Classifier: Programming Language :: Python
Classifier: Topic :: Software Development :: Libraries :: Python Modules
